vaultpass/__init__.py
vaultpass/vaultpass.py
vaultpass-1.0.18.data/scripts/vaultpass-direct.py
vaultpass-1.0.18.data/scripts/vaultpass.py
vaultpass-1.0.18.dist-info/METADATA
vaultpass-1.0.18.dist-info/WHEEL
vaultpass-1.0.18.dist-info/top_level.txt
vaultpass-1.0.18.dist-info/RECORD
