Metadata-Version: 2.1
Name: vaultpass
Version: 1.0.18
Summary: VaultPass: A CyberArk Search Script. Search for accounts and retrieve their passwords in the CyberArk elevated access management application. You can only retrieve accounts that you are able to view.
Home-page: https://github.com/mjackstewart/vaultpass
Author: Jack Stewart
Author-email: mjackstewart@gmail.com
License: Unilicense
Platform: UNKNOWN
Classifier: Development Status :: 1 - Planning
Classifier: Intended Audience :: Information Technology
Classifier: License :: Free for non-commercial use
Classifier: Operating System :: Microsoft :: Windows
Classifier: Operating System :: POSIX :: Linux
Classifier: Programming Language :: Python :: 3
Requires-Dist: certifi
Requires-Dist: charset-normalizer
Requires-Dist: click
Requires-Dist: colorama
Requires-Dist: enum34
Requires-Dist: idna
Requires-Dist: pexpect
Requires-Dist: ptyprocess
Requires-Dist: passpy (==1.0.2)
Requires-Dist: pypass
Requires-Dist: requests
Requires-Dist: typing-extensions
Requires-Dist: urllib3 (==1.26.6)
